greyhorse_renders/__init__.py
greyhorse_renders/abc.py
greyhorse_renders/controller.py
greyhorse_renders/py.typed
greyhorse_renders/conf/__init__.py
greyhorse_renders/conf/loader.py
greyhorse_renders/conf/parser.py
greyhorse_renders/private/__init__.py
greyhorse_renders/private/jinja.py
greyhorse_renders/private/simple.py
greyhorse_renders-0.4.26.dist-info/METADATA
greyhorse_renders-0.4.26.dist-info/WHEEL
greyhorse_renders-0.4.26.dist-info/RECORD
