Metadata-Version: 2.3
Name: greyhorse-renders
Version: 0.4.26
Summary: Greyhorse Renders library
Project-URL: Homepage, https://gitlab.com/max-plutonium/greyhorse
Project-URL: Repository, https://gitlab.com/max-plutonium/greyhorse
Author-email: Max Plutonium <plutonium.max@gmail.com>
Maintainer-email: Max Plutonium <plutonium.max@gmail.com>
License: MIT License
Keywords: jinja,rendering
Classifier: Development Status :: 4 - Beta
Classifier: Intended Audience :: Developers
Classifier: License :: OSI Approved :: MIT License
Classifier: Programming Language :: Python :: 3
Classifier: Programming Language :: Python :: 3.12
Classifier: Typing :: Typed
Requires-Python: >=3.12
Requires-Dist: greyhorse~=0.4.25
Provides-Extra: jinja
Requires-Dist: jinja2~=3.1.4; extra == 'jinja'
